LICENSE
README.md
setup.py
snitchpy/__init__.py
snitchpy.egg-info/PKG-INFO
snitchpy.egg-info/SOURCES.txt
snitchpy.egg-info/dependency_links.txt
snitchpy.egg-info/top_level.txt
snitchpy/metrics/__init__.py
snitchpy/tail/__init__.py
snitchpy/validation/__init__.py