Metadata-Version: 2.1
Name: snitchpy
Version: 0.0.18
Summary: Python client SDK for Streamdal's open source Snitch server
Home-page: https://github.com/streamdal/snitch-python-client
Author: Streamdal.com
Author-email: engineering@streamdal.com
License: MIT
Platform: UNKNOWN
Classifier: License :: OSI Approved :: MIT License
Classifier: Programming Language :: Python :: 3.8
Classifier: Programming Language :: Python :: 3.9
Classifier: Programming Language :: Python :: 3.10
Classifier: Programming Language :: Python :: 3.11
Requires-Python: >=3.8
License-File: LICENSE
